text2excel/__init__.py
text2excel/cli.py
text2excel/convert.py
text2excel/fmt.py
text2excel-0.4.3.dist-info/entry_points.txt
text2excel-0.4.3.dist-info/LICENSE
text2excel-0.4.3.dist-info/WHEEL
text2excel-0.4.3.dist-info/METADATA
text2excel-0.4.3.dist-info/RECORD
