Metadata-Version: 2.1
Name: text2excel
Version: 0.4.3
Summary: Converts to Excel XLSX from a TSV or CSV text file.
Home-page: https://github.com/harkabeeparolus/text2excel
License: MIT
Keywords: csv,tsv,excel,xlsx
Author: Fredrik Mellström
Author-email: 11281108+harkabeeparolus@users.noreply.github.com
Requires-Python: >=3.7,<4.0
Classifier: Environment :: Console
Classifier: Intended Audience :: Information Technology
Classifier: License :: OSI Approved :: MIT License
Classifier: Operating System :: OS Independent
Classifier: Programming Language :: Python :: 3
Classifier: Programming Language :: Python :: 3.10
Classifier: Programming Language :: Python :: 3.7
Classifier: Programming Language :: Python :: 3.8
Classifier: Programming Language :: Python :: 3.9
Classifier: Topic :: Text Processing
Classifier: Topic :: Utilities
Requires-Dist: importlib-metadata (>=3,<5); python_version < "3.8"
Requires-Dist: openpyxl (>=3.0.9,<4.0.0)
